sd_download/arg_parse.py
sd_download/download.py
sd_download/ensure_hook.py
sd_download/ensure_local_repo.py
sd_download/get_bearer_token.py
sd_download/get_software.py
sd_download/module_1.py
sd_download/parse_config.py
sd_download-0.1.4.dist-info/METADATA
sd_download-0.1.4.dist-info/WHEEL
sd_download-0.1.4.dist-info/top_level.txt
sd_download-0.1.4.dist-info/RECORD
