Metadata-Version: 2.1
Name: sd-download
Version: 0.1.4
Summary: Package to download files to the Robin Radar API
Home-page: https://bitbucket.org/robin-radar-systems/sd-api-download-pip-package.git
Author: Robin Radar Systems
Author-email: tivadar.kamondy@robinradar.com
License: MIT
Keywords: python
Platform: UNKNOWN
Requires-Dist: tqdm (>=4.62.0)
